bytestring.py
bytestring_test.py
bytestring-0.0.1.dist-info/DESCRIPTION.rst
bytestring-0.0.1.dist-info/METADATA
bytestring-0.0.1.dist-info/RECORD
bytestring-0.0.1.dist-info/WHEEL
bytestring-0.0.1.dist-info/entry_points.txt
bytestring-0.0.1.dist-info/metadata.json
bytestring-0.0.1.dist-info/top_level.txt
