Metadata-Version: 2.0
Name: bytestring
Version: 0.0.1
Summary: Convert integers into IEC binary strings and back
Home-page: UNKNOWN
Author: Ethan Dalool (voussoir)
Author-email: UNKNOWN
License: UNKNOWN
Platform: UNKNOWN
